chartlyrics/__init__.py
chartlyrics/__main__.py
chartlyrics/client.py
chartlyrics/lyrics.py
chartlyrics-0.1.7.dist-info/LICENSE
chartlyrics-0.1.7.dist-info/METADATA
chartlyrics-0.1.7.dist-info/WHEEL
chartlyrics-0.1.7.dist-info/RECORD
