Metadata-Version: 2.1
Name: chartlyrics
Version: 0.1.7
Summary: Wrapper for chartlyrics api: http://api.chartlyrics.com
Home-page: https://github.com/matheusfillipe/chartlyrics
License: MIT
Author: matheusfillipe
Author-email: matheusfillipeag@gmail.com
Requires-Python: >=3.8,<4.0
Classifier: License :: OSI Approved :: MIT License
Classifier: Programming Language :: Python :: 3
Classifier: Programming Language :: Python :: 3.8
Classifier: Programming Language :: Python :: 3.9
Classifier: Programming Language :: Python :: 3.10
Classifier: Programming Language :: Python :: 3.11
Classifier: Programming Language :: Python :: 3.12
Classifier: Programming Language :: Python :: 3.13
Requires-Dist: click (>=8.1.3,<9.0.0)
Requires-Dist: lxml (>=5.2.2,<6.0.0)
Requires-Dist: requests (>=2.28.1,<3.0.0)
Project-URL: Repository, https://github.com/matheusfillipe/chartlyrics
